cleez-0.1.14.dist-info/METADATA
cleez-0.1.14.dist-info/WHEEL
cleez-0.1.14.dist-info/entry_points.txt
cleez-0.1.14.dist-info/licenses/LICENSE
cleez/__init__.py
cleez/actions.py
cleez/argument.py
cleez/cleez.py
cleez/colors.py
cleez/command.py
cleez/exceptions.py
cleez/help.py
cleez/parser.py
cleez/testing.py
cleez-0.1.14.dist-info/RECORD
