Metadata-Version: 2.1
Name: cleez
Version: 0.1.14
Summary: Simple class-based CLI framework.
Author-Email: Abilian SAS <sf@abilian.com>
Classifier: Development Status :: 3 - Alpha
Classifier: Intended Audience :: Developers
Classifier: Natural Language :: English
Classifier: Programming Language :: Python :: 3
Classifier: Programming Language :: Python :: 3.9
Classifier: Programming Language :: Python :: 3.10
Classifier: Programming Language :: Python :: 3.11
Project-URL: homepage, https://github.com/abilian/cleez
Requires-Python: <4,>=3.9
Requires-Dist: termcolor~=3.0
